QuerysetPaginator/EvaluatedQuerysetPaginator.py
QuerysetPaginator/__init__.py
QuerysetPaginator-0.0.2.dist-info/LICENSE
QuerysetPaginator-0.0.2.dist-info/METADATA
QuerysetPaginator-0.0.2.dist-info/WHEEL
QuerysetPaginator-0.0.2.dist-info/top_level.txt
QuerysetPaginator-0.0.2.dist-info/RECORD
