Metadata-Version: 2.1
Name: QuerysetPaginator
Version: 0.0.2
Summary: This package helps in paginating evaluated querysets
Home-page: https://github.com/GetMeLive/queryset-paginator
Author: GetMeLive
Author-email: tech@getmelive.in
License: UNKNOWN
Platform: UNKNOWN
Classifier: Programming Language :: Python :: 3
Classifier: License :: OSI Approved :: MIT License
Classifier: Operating System :: OS Independent
